handy_converters/__init__.py
handy_converters/base64uuid.py
django_handy_converters-2019.3.dist-info/METADATA
django_handy_converters-2019.3.dist-info/WHEEL
django_handy_converters-2019.3.dist-info/top_level.txt
django_handy_converters-2019.3.dist-info/RECORD
